kling_motio_control/__init__.py
kling_motio_control-1768444.568.616.dist-info/licenses/LICENSE
kling_motio_control-1768444.568.616.dist-info/METADATA
kling_motio_control-1768444.568.616.dist-info/WHEEL
kling_motio_control-1768444.568.616.dist-info/top_level.txt
kling_motio_control-1768444.568.616.dist-info/RECORD
