Metadata-Version: 2.4
Name: kling-motio-control
Version: 1768444.568.616
Summary: High-quality integration for https://supermaker.ai/blog/what-is-kling-motion-control-ai-how-to-use-motion-control-ai-free-online/
Home-page: https://supermaker.ai/blog/what-is-kling-motion-control-ai-how-to-use-motion-control-ai-free-online/
Author: SuperMaker
Classifier: Programming Language :: Python :: 3
Classifier: License :: OSI Approved :: MIT License
Requires-Python: >=3.6
License-File: LICENSE
Dynamic: author
Dynamic: classifier
Dynamic: description
Dynamic: description-content-type
Dynamic: home-page
Dynamic: license-file
Dynamic: requires-python
Dynamic: summary
